xmlrepr/__init__.py
xmlrepr-0.1.0.dist-info/LICENSE.txt
xmlrepr-0.1.0.dist-info/METADATA
xmlrepr-0.1.0.dist-info/WHEEL
xmlrepr-0.1.0.dist-info/top_level.txt
xmlrepr-0.1.0.dist-info/RECORD
