Metadata-Version: 2.1
Name: xmlrepr
Version: 0.1.0
Summary: module for XML representations
Home-page: UNKNOWN
Author: Saad El-Sayed
Author-email: saadzahem7@gmail.com
License: UNKNOWN
Platform: UNKNOWN
Classifier: Programming Language :: Python :: 3
Classifier: License :: OSI Approved :: MIT License
Classifier: Operating System :: OS Independent
Requires-Python: >=3.6
License-File: LICENSE.txt
